batchdim/__init__.py
batchdim-0.1.0.dist-info/METADATA
batchdim-0.1.0.dist-info/WHEEL
batchdim-0.1.0.dist-info/licenses/LICENSE
batchdim-0.1.0.dist-info/RECORD
