Metadata-Version: 2.4
Name: batchdim
Version: 0.1.0
Summary: batchdim
Author-email: hello@batchdim.com
License-Expression: MIT
License-File: LICENSE
Requires-Python: >=3.9
